simple_icd_10_CM/__init__.py
simple_icd_10_CM/simple_icd_10_cm.py
simple_icd_10_CM/data/__init__.py
simple_icd_10_cm_new-1.1.2.dist-info/LICENSE
simple_icd_10_cm_new-1.1.2.dist-info/METADATA
simple_icd_10_cm_new-1.1.2.dist-info/WHEEL
simple_icd_10_cm_new-1.1.2.dist-info/top_level.txt
simple_icd_10_cm_new-1.1.2.dist-info/RECORD
