Metadata-Version: 2.1
Name: simple-icd-10-cm-new
Version: 1.1.2
Summary: A simple python library for ICD-10-CM codes
Home-page: https://github.com/StefanoTrv/simple_icd_10_CM
Author: Stefano Travasci
Author-email: stefanotravasci@gmail.com
Keywords: ICD-10-CM ICD-10 icd 10 CM codes clinical modification
Classifier: Programming Language :: Python :: 3
Classifier: License :: OSI Approved :: MIT License
Classifier: Operating System :: OS Independent
Requires-Python: >=3
License-File: LICENSE
